configfiles/__init__.py
configfiles/__main__.py
configfiles/auth.py
configfiles/gen/__init__.py
configfiles/gen/patcher.py
configfiles/local/__init__.py
configfiles/local/db.py
configfiles/local/filemon.py
configfiles/local/hashes.py
configfiles/repo/__init__.py
configfiles/repo/locks.py
configfiles/repo/obj.py
configfiles-0.3.1.dist-info/LICENSE
configfiles-0.3.1.dist-info/METADATA
configfiles-0.3.1.dist-info/WHEEL
configfiles-0.3.1.dist-info/entry_points.txt
configfiles-0.3.1.dist-info/top_level.txt
configfiles-0.3.1.dist-info/RECORD
