Metadata-Version: 2.1
Name: configfiles
Version: 0.3.1
Summary: A tool to manage config files across machines.
Home-page: https://github.com/mincrmatt12/configfiles
Author: Matthew Mirvish
License: MIT
Project-URL: Bug Tracker, https://github.com/mincrmatt12/configfiles/issues
Project-URL: Source Code, https://github.com/mincrmatt12/configfiles
Keywords: vcs configuration remote tool cli config management
Platform: UNKNOWN
Requires-Python: >=3.6
Requires-Dist: click
Requires-Dist: paramiko
Requires-Dist: diff-match-patch
